{
  "kind": "collectionType",
  "collectionName": "posts",
  "info": {
    "singularName": "post",
    "pluralName": "posts",
    "displayName": "post"
  },
  "options": {
    "draftAndPublish": true
  },
  "pluginOptions": {},
  "attributes": {
    "short_title": {
      "type": "string"
    },
    "title": {
      "type": "text"
    },
    "content": {
      "type": "richtext"
    },
    "deleted": {
      "type": "boolean"
    },
    "cover": {
      "allowedTypes": [
        "images",
        "files",
        "videos",
        "audios"
      ],
      "type": "media",
      "multiple": false
    }
  }
}
